hc_test
