Metadata-Version: 1.0
Name: hc-test
Version: 0.0.2
Summary: hc test pypi setup
Home-page: https://github.com/handongzhe/pypi_test
Author: handongzhe
Author-email: robbinjackly@gmail.com
License: UNKNOWN
Platform: UNKNOWN
